Metadata-Version: 2.4
Name: peakina
Version: 0.19.4
Summary: pandas readers on steroids (remote files, glob patterns, cache, etc.)
Author-email: Toucan Toco <dev@toucantoco.com>
License: BSD-3-Clause
Project-URL: homepage, https://github.com/ToucanToco/peakina
Project-URL: repository, https://github.com/ToucanToco/peakina
Project-URL: documentation, https://toucantoco.github.io/peakina
Classifier: Intended Audience :: Developers
Classifier: License :: OSI Approved :: BSD License
Classifier: Programming Language :: Python :: 3 :: Only
Classifier: Programming Language :: Python :: 3.10
Classifier: Programming Language :: Python :: 3.11
Classifier: Programming Language :: Python :: 3.12
Classifier: Programming Language :: Python :: 3.13
Classifier: Typing :: Typed
Requires-Python: <4.0,>=3.13
Requires-Dist: certifi
Requires-Dist: chardet<6,>=4
Requires-Dist: fastexcel[pandas]>=0.18.0
Requires-Dist: geopandas<2,>=1.0.0
Requires-Dist: jq<2.0.0,>=1.2.1
Requires-Dist: pandas<3.0.0,>=2
Requires-Dist: paramiko<4.1.0,>=2.9.2
Requires-Dist: pyarrow>=11
Requires-Dist: pydantic<3.0.0,>=2.4.2
Requires-Dist: python-slugify<9.0.0,>=5.0.2
Requires-Dist: s3fs>=2022.1
Requires-Dist: urllib3<3.0.0,>=1.26.8
Requires-Dist: xlrd<3.0.0,>=2.0.1
Requires-Dist: xmltodict<2,>=0.12.0
